hindImageOcr/__init__.py
hindImageOcr/hindi_image_translater.py
hindImageOcr-1.dist-info/LICENSE
hindImageOcr-1.dist-info/METADATA
hindImageOcr-1.dist-info/WHEEL
hindImageOcr-1.dist-info/top_level.txt
hindImageOcr-1.dist-info/RECORD
