Metadata-Version: 2.1
Name: hindImageOcr
Version: 1
License-File: LICENSE
Requires-Dist: easyocr >=1.5.0
Requires-Dist: googletrans ==4.0.0-rc1
Requires-Dist: Pillow >=9
